[
    {
        "name": "im65.jpg",
        "tags": [
            "butterfly",
            "nature"
        ]
    },
    {
        "name": "im94.jpg",
        "tags": [
            "lion",
            "cat",
            "animal",
            "pet"
        ]
    },
    {
        "name": "im112.jpg",
        "tags": [
            "flower",
            "nature"
        ]
    },
    {
        "name": "im781.jpg",
        "tags": [
            "bird",
            "animal"
        ]
    },
    {
        "name": "im866.jpg",
        "tags": [
            "tree",
            "nature"
        ]
    },
    {
        "name": "im1083.jpg",
        "tags": [
            "man",
            "people",
            "guitar"
        ]
    },
    {
        "name": "im6190.jpg",
        "tags": [
            "dog",
            "animal",
            "pet"
        ]
    }
]